Metadata-Version: 1.0
Name: imagy
Version: 0.4.0
Summary: A daemon to automatically handle image optimization
Home-page: https://github.com/doda/imagy
Author: Dominik Dabrowski
Author-email: dominik@silberrock.com
License: Copyright (c) 2012, Dominik Dabrowski
